pygad/__init__.py
pygad/pygad.py
pygad/cnn/__init__.py
pygad/cnn/cnn.py
pygad/gacnn/__init__.py
pygad/gacnn/gacnn.py
pygad/gann/__init__.py
pygad/gann/gann.py
pygad/helper/__init__.py
pygad/helper/misc.py
pygad/helper/unique.py
pygad/kerasga/__init__.py
pygad/kerasga/kerasga.py
pygad/nn/__init__.py
pygad/nn/nn.py
pygad/torchga/__init__.py
pygad/torchga/torchga.py
pygad/utils/__init__.py
pygad/utils/crossover.py
pygad/utils/mutation.py
pygad/utils/nsga2.py
pygad/utils/parent_selection.py
pygad/visualize/__init__.py
pygad/visualize/plot.py
pygad-3.5.0.dist-info/LICENSE
pygad-3.5.0.dist-info/METADATA
pygad-3.5.0.dist-info/WHEEL
pygad-3.5.0.dist-info/top_level.txt
pygad-3.5.0.dist-info/RECORD
