Metadata-Version: 2.1
Name: pygad
Version: 3.5.0
Summary: PyGAD: A Python Library for Building the Genetic Algorithm and Training Machine Learning Algoithms (Keras & PyTorch).
Home-page: https://github.com/ahmedfgad/GeneticAlgorithmPython
Author: Ahmed Fawzy Gad
Author-email: Ahmed Gad <ahmed.f.gad@gmail.com>
Maintainer-email: Ahmed Gad <ahmed.f.gad@gmail.com>
License: Copyright GeneticAlgorithmPython Contributors
Project-URL: Homepage, https://github.com/ahmedfgad/GeneticAlgorithmPython
Project-URL: Documentation, https://pygad.readthedocs.io
Project-URL: GitHub Repository, https://github.com/ahmedfgad/GeneticAlgorithmPython
Project-URL: PyPI Project, https://pypi.org/project/pygad
Project-URL: Conda Forge Project, https://anaconda.org/conda-forge/pygad
Project-URL: Donation Stripe, https://donate.stripe.com/eVa5kO866elKgM0144
Project-URL: Donation Open Collective, https://opencollective.com/pygad
Project-URL: Donation Paypal, http://paypal.me/ahmedfgad
Keywords: genetic algorithm,GA,optimization,evolutionary algorithm,natural evolution,pygad,machine learning,deep learning,neural networks,tensorflow,keras,pytorch
Classifier: License :: OSI Approved :: BSD License
Classifier: Programming Language :: Python
Classifier: Programming Language :: Python :: 3
Classifier: Natural Language :: English
Classifier: Operating System :: OS Independent
Classifier: Topic :: Scientific/Engineering
Classifier: Topic :: Scientific/Engineering :: Bio-Informatics
Classifier: Topic :: Scientific/Engineering :: Artificial Intelligence
Classifier: Topic :: Software Development
Classifier: Topic :: Utilities
Classifier: Intended Audience :: Information Technology
Classifier: Intended Audience :: Science/Research
Classifier: Intended Audience :: Developers
Classifier: Intended Audience :: Education
Classifier: Intended Audience :: Other Audience
Requires-Python: >=3
Provides-Extra: deep_learning
License-File: LICENSE
